
{
  "workbench.iconTheme": "eq-material-theme-icons-darker",
  "go.gopath": "/Users/samuellundgren/gocode",
  "workbench.colorTheme": "Monokai Dimmed",
  "javascript.format.enable": false,
  "prettier.eslintIntegration": true,
  "[javascript]": {
    "editor.formatOnSave": true
  },
  "window.zoomLevel": 0,
  "javascript.updateImportsOnFileMove.enabled": "never",
  "explorer.confirmDelete": false,
  "files.exclude": {
    "**/.git": true,
    "**/.svn": true,
    "**/.hg": true,
    "**/CVS": true,
    "**/.DS_Store": true,
    "**/node_modules": true,
    "**/coverage": true,
    "**/.next": true,
    "**/package-lock.json": true,
    "**/yarn.lock": true,
    "**/*.pyc": true
  },
  "editor.fontFamily": "Hack",
  "editor.cursorBlinking": "solid",
  "editor.minimap.enabled": false,
  "explorer.openEditors.visible": 0,

  "python.formatting.provider": "black",
  "python.formatting.blackPath": "/usr/local/bin/black",
  "editor.formatOnSave": true,
  "python.sortImports.path": "",
  "[java]": {},
  "explorer.confirmDragAndDrop": false,
  "python.venvPath": "${workspaceFolder}/env",
  "python.pythonPath": "/usr/bin/python",
  "gitlens.codeLens.enabled": false,
  "editor.showFoldingControls": "always"
  //   "editor.codeActionsOnSave": {
  //     "source.organizeImports": true
  //   }
}
